django_query_capture/__init__.py
django_query_capture/capture.py
django_query_capture/classify.py
django_query_capture/decorators.py
django_query_capture/middleware.py
django_query_capture/presenter/__init__.py
django_query_capture/presenter/base.py
django_query_capture/presenter/only_slow_query.py
django_query_capture/presenter/pretty.py
django_query_capture/presenter/raw_line.py
django_query_capture/presenter/simple.py
django_query_capture/settings.py
django_query_capture/test_utils.py
django_query_capture/utils.py
django_query_capture-0.3.2.dist-info/entry_points.txt
django_query_capture-0.3.2.dist-info/LICENSE
django_query_capture-0.3.2.dist-info/WHEEL
django_query_capture-0.3.2.dist-info/METADATA
django_query_capture-0.3.2.dist-info/RECORD
