Metadata-Version: 2.1
Name: django-query-capture
Version: 0.3.2
Summary: Shows queries, detects N+1 in Django, Simple to use, Can Customize Console Result
Home-page: https://github.com/ashekr/django-query-capture
License: MIT
Keywords: django,query,performance,database,n+1
Author: AsheKR
Author-email: tech@ashe.kr
Requires-Python: >=3.8,<4.0
Classifier: Development Status :: 3 - Alpha
Classifier: Framework :: Django :: 3.2
Classifier: Framework :: Django :: 4.0
Classifier: Intended Audience :: Developers
Classifier: License :: OSI Approved :: MIT License
Classifier: Natural Language :: English
Classifier: Natural Language :: Korean
Classifier: Operating System :: OS Independent
Classifier: Programming Language :: Python :: 3
Classifier: Programming Language :: Python :: 3.10
Classifier: Programming Language :: Python :: 3.8
Classifier: Programming Language :: Python :: 3.9
Classifier: Topic :: Software Development :: Libraries :: Python Modules
Requires-Dist: Django (>=2.2)
Requires-Dist: Pygments (>=2.11.2,<3.0.0)
Requires-Dist: tabulate (>=0.8.9,<0.9.0)
Project-URL: Repository, https://github.com/ashekr/django-query-capture
